anisofilter/__init__.py
anisofilter/anisofilter.py
anisofilter/libpcd_kdtree_knn.dll
anisofilter/libpcd_kdtree_knn.so
anisofilter/libpcd_kdtree_knn_mac.so
anisofilter/libpcd_kdtree_radius.dll
anisofilter/libpcd_kdtree_radius.so
anisofilter/libpcd_kdtree_radius_mac.so
anisofilter/libpcd_std_est_var_numk.dll
anisofilter/libpcd_std_est_var_numk.so
anisofilter/libpcd_std_est_var_numk_mac.so
anisofilter/libsquare_neigh_ici_denoi_recur_pure_c_parallel.dll
anisofilter/libsquare_neigh_ici_denoi_recur_pure_c_parallel.so
anisofilter/libsquare_neigh_ici_denoi_recur_pure_c_parallel_mac.so
anisofilter/utilities.py
anisofilter-1.0.6.dist-info/LICENSE
anisofilter-1.0.6.dist-info/METADATA
anisofilter-1.0.6.dist-info/WHEEL
anisofilter-1.0.6.dist-info/top_level.txt
anisofilter-1.0.6.dist-info/RECORD
