Metadata-Version: 2.1
Name: anisofilter
Version: 1.0.6
Summary: Anisotropic filter for 3D point clouds
Home-page: https://webpages.tuni.fi/foi/PointCloudFiltering/
Author: Zhongwei Xu
Author-email: xu@noiselessimaging.com
Classifier: Programming Language :: Python :: 3
Classifier: License :: Free for non-commercial use
Classifier: Intended Audience :: Education
Classifier: Intended Audience :: Science/Research
Classifier: Operating System :: POSIX :: Linux
Classifier: Operating System :: Microsoft :: Windows
Classifier: Operating System :: MacOS
Classifier: Topic :: Scientific/Engineering :: Information Analysis
Classifier: Topic :: Scientific/Engineering :: Mathematics
Classifier: Topic :: Software Development :: Libraries :: Python Modules
Requires-Python: >=3.6
License-File: LICENSE
Requires-Dist: numpy
Requires-Dist: scikit-learn
